ckanext/__init__.py
ckanext/msal/__init__.py
ckanext/msal/config.py
ckanext/msal/middleware.py
ckanext/msal/plugin.py
ckanext/msal/user.py
ckanext/msal/utils.py
ckanext/msal/views.py
ckanext/msal/assets/webassets.yml
ckanext/msal/tests/__init__.py
ckanext/msal/tests/fixtures.py
ckanext/msal/tests/test_user.py
ckanext/msal/tests/test_utils.py
ckanext_msal-1.6.0.dist-info/LICENSE
ckanext_msal-1.6.0.dist-info/METADATA
ckanext_msal-1.6.0.dist-info/WHEEL
ckanext_msal-1.6.0.dist-info/entry_points.txt
ckanext_msal-1.6.0.dist-info/top_level.txt
ckanext_msal-1.6.0.dist-info/RECORD
